frozen_box/__init__.py
frozen_box/exception.py
frozen_box/frozen_class.py
frozen_box-0.0.1.dist-info/LICENSE
frozen_box-0.0.1.dist-info/METADATA
frozen_box-0.0.1.dist-info/WHEEL
frozen_box-0.0.1.dist-info/top_level.txt
frozen_box-0.0.1.dist-info/RECORD
